pygridsim/__init__.py
pygridsim/configs.py
pygridsim/core.py
pygridsim/defaults.py
pygridsim/enums.py
pygridsim/lines.py
pygridsim/parameters.py
pygridsim/results.py
pygridsim-0.1.0.dist-info/licenses/LICENSE
pygridsim-0.1.0.dist-info/METADATA
pygridsim-0.1.0.dist-info/WHEEL
pygridsim-0.1.0.dist-info/top_level.txt
pygridsim-0.1.0.dist-info/RECORD
