Metadata-Version: 2.4
Name: pygridsim
Version: 0.1.0
Summary: Package to simulate OpenDSS circuits on Python
Home-page: https://github.com/amzhao/PyGridSim
Author: Angela Zhao
Author-email: amzhao@mit.edu
License: MIT license
Keywords: pygridsim pygridsim PyGridSim
Classifier: Development Status :: 2 - Pre-Alpha
Classifier: Intended Audience :: Developers
Classifier: License :: OSI Approved :: MIT License
Classifier: Natural Language :: English
Classifier: Programming Language :: Python :: 3
Classifier: Programming Language :: Python :: 3.5
Classifier: Programming Language :: Python :: 3.6
Classifier: Programming Language :: Python :: 3.7
Classifier: Programming Language :: Python :: 3.8
Requires-Python: >=3.10, <3.13
License-File: LICENSE
Requires-Dist: altdss>=0.2.4
Provides-Extra: test
Requires-Dist: pytest>=3.4.2; extra == "test"
Requires-Dist: pytest-cov>=2.6.0; extra == "test"
Provides-Extra: dev
Requires-Dist: bumpversion>=0.5.3; extra == "dev"
Requires-Dist: pip>=9.0.1; extra == "dev"
Requires-Dist: watchdog>=0.8.3; extra == "dev"
Requires-Dist: m2r2<4; extra == "dev"
Requires-Dist: docutils<1,>=0.12; extra == "dev"
Requires-Dist: nbsphinx<1,>=0.5.0; extra == "dev"
Requires-Dist: sphinx_toolbox<4,>=2.5; extra == "dev"
Requires-Dist: Sphinx<7,>=3; extra == "dev"
Requires-Dist: markupsafe<3; extra == "dev"
Requires-Dist: ipython<12,>=6.5; extra == "dev"
Requires-Dist: sphinx_rtd_theme<0.5,>=0.2.4; extra == "dev"
Requires-Dist: flake8>=3.7.7; extra == "dev"
Requires-Dist: isort>=4.3.4; extra == "dev"
Requires-Dist: autoflake>=1.2; extra == "dev"
Requires-Dist: autopep8>=1.4.3; extra == "dev"
Requires-Dist: twine>=1.10.0; extra == "dev"
Requires-Dist: wheel>=0.30.0; extra == "dev"
Requires-Dist: coverage>=4.5.1; extra == "dev"
Requires-Dist: tox>=2.9.1; extra == "dev"
Requires-Dist: pytest>=3.4.2; extra == "dev"
Requires-Dist: pytest-cov>=2.6.0; extra == "dev"
Dynamic: author
Dynamic: author-email
Dynamic: classifier
Dynamic: description
Dynamic: description-content-type
Dynamic: home-page
Dynamic: keywords
Dynamic: license
Dynamic: license-file
Dynamic: provides-extra
Dynamic: requires-dist
Dynamic: requires-python
Dynamic: summary
